mhdwriter/__init__.py
mhdwriter/args.py
mhdwriter/header.py
mhdwriter/writer.py
mhdwriter-0.2.0.9.dist-info/METADATA
mhdwriter-0.2.0.9.dist-info/WHEEL
mhdwriter-0.2.0.9.dist-info/RECORD
