Metadata-Version: 2.3
Name: mhdwriter
Version: 0.2.0.9
Summary: 
Author: Eli White
Author-email: eli.white@emitimaging.com
Requires-Python: >=3.10,<3.13
Classifier: Programming Language :: Python :: 3
Classifier: Programming Language :: Python :: 3.10
Classifier: Programming Language :: Python :: 3.11
Classifier: Programming Language :: Python :: 3.12
Requires-Dist: imagecodecs (>=2023.8.12,<2024.0.0)
Requires-Dist: opencv-python (>=4.9.0.80,<5.0.0.0)
